setup.py
bin/jjrender
jinja2_utilities/__init__.py
jinja2_utilities.egg-info/PKG-INFO
jinja2_utilities.egg-info/SOURCES.txt
jinja2_utilities.egg-info/dependency_links.txt
jinja2_utilities.egg-info/not-zip-safe
jinja2_utilities.egg-info/requires.txt
jinja2_utilities.egg-info/top_level.txt