Metadata-Version: 1.0
Name: jinja2-utilities
Version: 0.1
Summary: Jinja2 utilities
Home-page: http://github.com/emayssat/jjrender
Author: Emmanuel Mayssat
Author-email: emmanuel.mayssat@aya.yale.edu
License: MIT
Platform: UNKNOWN
